{
  "last_updated": "29/09/2025 06:18",
  "total_commodities": 16,
  "commodities": [
    {
      "category": "Energy",
      "name": "Gold",
      "price": "3,815.63",
      "percentage_change": "1.41%",
      "absolute_change": "52.92",
      "unit": "USD per Troy Ounce",
      "market_time": "02:13:00 AM",
      "trend": "up"
    },
    {
      "category": "Energy",
      "name": "Palladium",
      "price": "1,299.50",
      "percentage_change": "2.20%",
      "absolute_change": "28.00",
      "unit": "USD per Troy Ounce",
      "market_time": "02:13:00 AM",
      "trend": "up"
    },
    {
      "category": "Energy",
      "name": "Platinum",
      "price": "1,623.50",
      "percentage_change": "3.18%",
      "absolute_change": "50.00",
      "unit": "USD per Troy Ounce",
      "market_time": "02:13:00 AM",
      "trend": "up"
    },
    {
      "category": "Energy",
      "name": "Silver",
      "price": "46.99",
      "percentage_change": "2.06%",
      "absolute_change": "0.95",
      "unit": "USD per Troy Ounce",
      "market_time": "02:13:00 AM",
      "trend": "up"
    },
    {
      "category": "Industrial Metals",
      "name": "Natural Gas (Henry Hub)",
      "price": "3.16",
      "percentage_change": "10.52%",
      "absolute_change": "0.30",
      "unit": "USD per MMBtu",
      "market_time": "02:13:00 AM",
      "trend": "up"
    },
    {
      "category": "Industrial Metals",
      "name": "Heating Oil",
      "price": "63.93",
      "percentage_change": "-0.41%",
      "absolute_change": "-0.26",
      "unit": "USD per 100 Liter",
      "market_time": "02:11:00 AM",
      "trend": "down"
    },
    {
      "category": "Industrial Metals",
      "name": "Coal",
      "price": "92.95",
      "percentage_change": "0.27%",
      "absolute_change": "0.25",
      "unit": "per Ton",
      "market_time": "9/26/2025",
      "trend": "up"
    },
    {
      "category": "Industrial Metals",
      "name": "RBOB Gasoline",
      "price": "2.03",
      "percentage_change": "0.40%",
      "absolute_change": "0.01",
      "unit": "per Gallone",
      "market_time": "02:12:00 AM",
      "trend": "up"
    },
    {
      "category": "Industrial Metals",
      "name": "Oil (Brent)",
      "price": "69.73",
      "percentage_change": "-0.03%",
      "absolute_change": "-0.02",
      "unit": "USD per Barrel",
      "market_time": "02:03:00 AM",
      "trend": "down"
    },
    {
      "category": "Industrial Metals",
      "name": "Oil (WTI)",
      "price": "65.29",
      "percentage_change": "0.17%",
      "absolute_change": "0.11",
      "unit": "USD per Barrel",
      "market_time": "02:13:00 AM",
      "trend": "up"
    },
    {
      "category": "Agriculture",
      "name": "Aluminium",
      "price": "2,655.83",
      "percentage_change": "0.09%",
      "absolute_change": "2.28",
      "unit": "USD per Ton",
      "market_time": "9/26/2025",
      "trend": "up"
    },
    {
      "category": "Agriculture",
      "name": "Lead",
      "price": "1,957.50",
      "percentage_change": "-0.40%",
      "absolute_change": "-7.90",
      "unit": "USD per Ton",
      "market_time": "9/26/2025",
      "trend": "down"
    },
    {
      "category": "Agriculture",
      "name": "Copper",
      "price": "10,125.35",
      "percentage_change": "-1.92%",
      "absolute_change": "-198.15",
      "unit": "USD per Ton",
      "market_time": "9/26/2025",
      "trend": "down"
    },
    {
      "category": "Agriculture",
      "name": "Nickel",
      "price": "15,031.00",
      "percentage_change": "-1.64%",
      "absolute_change": "-250.00",
      "unit": "USD per Ton",
      "market_time": "9/26/2025",
      "trend": "down"
    },
    {
      "category": "Agriculture",
      "name": "Zinc",
      "price": "2,934.15",
      "percentage_change": "-2.56%",
      "absolute_change": "-77.00",
      "unit": "USD per Ton",
      "market_time": "9/26/2025",
      "trend": "down"
    },
    {
      "category": "Agriculture",
      "name": "Tin",
      "price": "34,436.50",
      "percentage_change": "0.03%",
      "absolute_change": "10.00",
      "unit": "USD per Ton",
      "market_time": "9/26/2025",
      "trend": "up"
    }
  ]
}