{
  "last_updated": "21/05/2026 19:42",
  "total_commodities": 16,
  "commodities": [
    {
      "category": "Energy",
      "name": "Gold",
      "price": "4,541.15",
      "percentage_change": "-0.09%",
      "absolute_change": "-4.02",
      "unit": "USD per Troy Ounce",
      "market_time": "03:37:00 PM",
      "trend": "down"
    },
    {
      "category": "Energy",
      "name": "Palladium",
      "price": "1,397.00",
      "percentage_change": "1.71%",
      "absolute_change": "23.50",
      "unit": "USD per Troy Ounce",
      "market_time": "03:36:00 PM",
      "trend": "up"
    },
    {
      "category": "Energy",
      "name": "Platinum",
      "price": "1,969.50",
      "percentage_change": "0.77%",
      "absolute_change": "15.00",
      "unit": "USD per Troy Ounce",
      "market_time": "03:37:00 PM",
      "trend": "up"
    },
    {
      "category": "Energy",
      "name": "Silver",
      "price": "76.58",
      "percentage_change": "0.72%",
      "absolute_change": "0.55",
      "unit": "USD per Troy Ounce",
      "market_time": "03:37:00 PM",
      "trend": "up"
    },
    {
      "category": "Industrial Metals",
      "name": "Natural Gas (Henry Hub)",
      "price": "2.99",
      "percentage_change": "-0.47%",
      "absolute_change": "-0.01",
      "unit": "USD per MMBtu",
      "market_time": "03:37:00 PM",
      "trend": "down"
    },
    {
      "category": "Industrial Metals",
      "name": "Heating Oil",
      "price": "102.23",
      "percentage_change": "-2.03%",
      "absolute_change": "-2.11",
      "unit": "USD per 100 Liter",
      "market_time": "03:37:00 PM",
      "trend": "down"
    },
    {
      "category": "Industrial Metals",
      "name": "Coal",
      "price": "112.55",
      "percentage_change": "0.04%",
      "absolute_change": "0.05",
      "unit": "per Ton",
      "market_time": "12:46:00 PM",
      "trend": "up"
    },
    {
      "category": "Industrial Metals",
      "name": "RBOB Gasoline",
      "price": "3.41",
      "percentage_change": "-2.21%",
      "absolute_change": "-0.08",
      "unit": "per Gallone",
      "market_time": "03:35:00 PM",
      "trend": "down"
    },
    {
      "category": "Industrial Metals",
      "name": "Oil (Brent)",
      "price": "103.92",
      "percentage_change": "-1.18%",
      "absolute_change": "-1.24",
      "unit": "USD per Barrel",
      "market_time": "03:27:00 PM",
      "trend": "down"
    },
    {
      "category": "Industrial Metals",
      "name": "Oil (WTI)",
      "price": "97.26",
      "percentage_change": "-1.02%",
      "absolute_change": "-1.00",
      "unit": "USD per Barrel",
      "market_time": "03:38:00 PM",
      "trend": "down"
    },
    {
      "category": "Agriculture",
      "name": "Aluminium",
      "price": "3,610.63",
      "percentage_change": "0.30%",
      "absolute_change": "10.65",
      "unit": "USD per Ton",
      "market_time": "5/20/2026",
      "trend": "up"
    },
    {
      "category": "Agriculture",
      "name": "Lead",
      "price": "1,966.70",
      "percentage_change": "0.86%",
      "absolute_change": "16.70",
      "unit": "USD per Ton",
      "market_time": "5/20/2026",
      "trend": "up"
    },
    {
      "category": "Agriculture",
      "name": "Copper",
      "price": "13,416.70",
      "percentage_change": "0.05%",
      "absolute_change": "6.70",
      "unit": "USD per Ton",
      "market_time": "5/20/2026",
      "trend": "up"
    },
    {
      "category": "Agriculture",
      "name": "Nickel",
      "price": "18,594.00",
      "percentage_change": "-1.07%",
      "absolute_change": "-201.00",
      "unit": "USD per Ton",
      "market_time": "5/20/2026",
      "trend": "down"
    },
    {
      "category": "Agriculture",
      "name": "Zinc",
      "price": "3,518.20",
      "percentage_change": "0.06%",
      "absolute_change": "2.20",
      "unit": "USD per Ton",
      "market_time": "5/20/2026",
      "trend": "up"
    },
    {
      "category": "Agriculture",
      "name": "Tin",
      "price": "54,194.00",
      "percentage_change": "2.64%",
      "absolute_change": "1,395.50",
      "unit": "USD per Ton",
      "market_time": "5/20/2026",
      "trend": "up"
    }
  ]
}