{
  "last_updated": "05/12/2025 18:15",
  "total_commodities": 16,
  "commodities": [
    {
      "category": "Energy",
      "name": "Gold",
      "price": "4,218.29",
      "percentage_change": "0.22%",
      "absolute_change": "9.40",
      "unit": "USD per Troy Ounce",
      "market_time": "01:10:00 PM",
      "trend": "up"
    },
    {
      "category": "Energy",
      "name": "Palladium",
      "price": "1,468.50",
      "percentage_change": "1.56%",
      "absolute_change": "22.50",
      "unit": "USD per Troy Ounce",
      "market_time": "01:10:00 PM",
      "trend": "up"
    },
    {
      "category": "Energy",
      "name": "Platinum",
      "price": "1,649.50",
      "percentage_change": "-0.06%",
      "absolute_change": "-1.00",
      "unit": "USD per Troy Ounce",
      "market_time": "01:10:00 PM",
      "trend": "down"
    },
    {
      "category": "Energy",
      "name": "Silver",
      "price": "58.68",
      "percentage_change": "2.71%",
      "absolute_change": "1.55",
      "unit": "USD per Troy Ounce",
      "market_time": "01:11:00 PM",
      "trend": "up"
    },
    {
      "category": "Industrial Metals",
      "name": "Natural Gas (Henry Hub)",
      "price": "5.43",
      "percentage_change": "7.33%",
      "absolute_change": "0.37",
      "unit": "USD per MMBtu",
      "market_time": "01:10:00 PM",
      "trend": "up"
    },
    {
      "category": "Industrial Metals",
      "name": "Heating Oil",
      "price": "62.87",
      "percentage_change": "3.48%",
      "absolute_change": "2.11",
      "unit": "USD per 100 Liter",
      "market_time": "01:10:00 PM",
      "trend": "up"
    },
    {
      "category": "Industrial Metals",
      "name": "Coal",
      "price": "97.25",
      "percentage_change": "0.26%",
      "absolute_change": "0.25",
      "unit": "per Ton",
      "market_time": "12:56:00 PM",
      "trend": "up"
    },
    {
      "category": "Industrial Metals",
      "name": "RBOB Gasoline",
      "price": "1.84",
      "percentage_change": "0.77%",
      "absolute_change": "0.01",
      "unit": "per Gallone",
      "market_time": "01:10:00 PM",
      "trend": "up"
    },
    {
      "category": "Industrial Metals",
      "name": "Oil (Brent)",
      "price": "63.91",
      "percentage_change": "0.85%",
      "absolute_change": "0.54",
      "unit": "USD per Barrel",
      "market_time": "01:00:00 PM",
      "trend": "up"
    },
    {
      "category": "Industrial Metals",
      "name": "Oil (WTI)",
      "price": "60.20",
      "percentage_change": "0.89%",
      "absolute_change": "0.53",
      "unit": "USD per Barrel",
      "market_time": "01:10:00 PM",
      "trend": "up"
    },
    {
      "category": "Agriculture",
      "name": "Aluminium",
      "price": "2,907.15",
      "percentage_change": "0.54%",
      "absolute_change": "15.56",
      "unit": "USD per Ton",
      "market_time": "12/4/2025",
      "trend": "up"
    },
    {
      "category": "Agriculture",
      "name": "Lead",
      "price": "1,961.00",
      "percentage_change": "0.01%",
      "absolute_change": "0.15",
      "unit": "USD per Ton",
      "market_time": "12/4/2025",
      "trend": "up"
    },
    {
      "category": "Agriculture",
      "name": "Copper",
      "price": "11,472.00",
      "percentage_change": "0.31%",
      "absolute_change": "35.85",
      "unit": "USD per Ton",
      "market_time": "12/4/2025",
      "trend": "up"
    },
    {
      "category": "Agriculture",
      "name": "Nickel",
      "price": "14,722.50",
      "percentage_change": "0.29%",
      "absolute_change": "42.50",
      "unit": "USD per Ton",
      "market_time": "12/4/2025",
      "trend": "up"
    },
    {
      "category": "Agriculture",
      "name": "Zinc",
      "price": "3,226.00",
      "percentage_change": "-0.44%",
      "absolute_change": "-14.15",
      "unit": "USD per Ton",
      "market_time": "12/4/2025",
      "trend": "down"
    },
    {
      "category": "Agriculture",
      "name": "Tin",
      "price": "40,293.50",
      "percentage_change": "0.92%",
      "absolute_change": "367.50",
      "unit": "USD per Ton",
      "market_time": "12/4/2025",
      "trend": "up"
    }
  ]
}