{
  "last_updated": "17/02/2026 12:38",
  "total_commodities": 16,
  "commodities": [
    {
      "category": "Energy",
      "name": "Gold",
      "price": "4,942.49",
      "percentage_change": "-1.00%",
      "absolute_change": "-49.98",
      "unit": "USD per Troy Ounce",
      "market_time": "07:31:00 AM",
      "trend": "down"
    },
    {
      "category": "Energy",
      "name": "Palladium",
      "price": "1,680.00",
      "percentage_change": "-3.97%",
      "absolute_change": "-69.50",
      "unit": "USD per Troy Ounce",
      "market_time": "07:31:00 AM",
      "trend": "down"
    },
    {
      "category": "Energy",
      "name": "Platinum",
      "price": "2,025.00",
      "percentage_change": "-1.07%",
      "absolute_change": "-22.00",
      "unit": "USD per Troy Ounce",
      "market_time": "07:31:00 AM",
      "trend": "down"
    },
    {
      "category": "Energy",
      "name": "Silver",
      "price": "75.11",
      "percentage_change": "-1.96%",
      "absolute_change": "-1.50",
      "unit": "USD per Troy Ounce",
      "market_time": "07:31:00 AM",
      "trend": "down"
    },
    {
      "category": "Industrial Metals",
      "name": "Natural Gas (Henry Hub)",
      "price": "3.14",
      "percentage_change": "1.16%",
      "absolute_change": "0.04",
      "unit": "USD per MMBtu",
      "market_time": "07:31:00 AM",
      "trend": "up"
    },
    {
      "category": "Industrial Metals",
      "name": "Heating Oil",
      "price": "63.14",
      "percentage_change": "%",
      "absolute_change": "",
      "unit": "USD per 100 Liter",
      "market_time": "2/16/2026",
      "trend": "neutral"
    },
    {
      "category": "Industrial Metals",
      "name": "Coal",
      "price": "104.25",
      "percentage_change": "-1.04%",
      "absolute_change": "-1.10",
      "unit": "per Ton",
      "market_time": "03:59:00 AM",
      "trend": "down"
    },
    {
      "category": "Industrial Metals",
      "name": "RBOB Gasoline",
      "price": "1.91",
      "percentage_change": "-0.31%",
      "absolute_change": "-0.01",
      "unit": "per Gallone",
      "market_time": "2/16/2026",
      "trend": "down"
    },
    {
      "category": "Industrial Metals",
      "name": "Oil (Brent)",
      "price": "68.70",
      "percentage_change": "0.17%",
      "absolute_change": "0.12",
      "unit": "USD per Barrel",
      "market_time": "07:21:00 AM",
      "trend": "up"
    },
    {
      "category": "Industrial Metals",
      "name": "Oil (WTI)",
      "price": "63.01",
      "percentage_change": "0.19%",
      "absolute_change": "0.12",
      "unit": "USD per Barrel",
      "market_time": "2/16/2026",
      "trend": "up"
    },
    {
      "category": "Agriculture",
      "name": "Aluminium",
      "price": "3,076.01",
      "percentage_change": "0.60%",
      "absolute_change": "18.47",
      "unit": "USD per Ton",
      "market_time": "2/16/2026",
      "trend": "up"
    },
    {
      "category": "Agriculture",
      "name": "Lead",
      "price": "1,902.35",
      "percentage_change": "-0.81%",
      "absolute_change": "-15.50",
      "unit": "USD per Ton",
      "market_time": "2/16/2026",
      "trend": "down"
    },
    {
      "category": "Agriculture",
      "name": "Copper",
      "price": "12,756.35",
      "percentage_change": "0.30%",
      "absolute_change": "37.60",
      "unit": "USD per Ton",
      "market_time": "2/16/2026",
      "trend": "up"
    },
    {
      "category": "Agriculture",
      "name": "Nickel",
      "price": "16,758.50",
      "percentage_change": "-0.24%",
      "absolute_change": "-40.50",
      "unit": "USD per Ton",
      "market_time": "2/16/2026",
      "trend": "down"
    },
    {
      "category": "Agriculture",
      "name": "Zinc",
      "price": "3,253.00",
      "percentage_change": "-1.25%",
      "absolute_change": "-41.20",
      "unit": "USD per Ton",
      "market_time": "2/16/2026",
      "trend": "down"
    },
    {
      "category": "Agriculture",
      "name": "Tin",
      "price": "46,291.50",
      "percentage_change": "-4.06%",
      "absolute_change": "-1,959.50",
      "unit": "USD per Ton",
      "market_time": "2/16/2026",
      "trend": "down"
    }
  ]
}